GODBOY/__init__.py
GODBOY/__main__.py
GODBOY/config.py
GODBOY/core.py
GODBOY/events.py
GODBOY/heroku.py
GODBOY/process.py
GODBOY/utils.py
GODBOY/variables.py
GODBOY/version.py
GODBOY-0.0.4.dist-info/METADATA
GODBOY-0.0.4.dist-info/WHEEL
GODBOY-0.0.4.dist-info/top_level.txt
GODBOY-0.0.4.dist-info/RECORD
