Metadata-Version: 2.1
Name: GODBOY
Version: 0.0.4
Summary: A Secure  and Powerful Python-Telethon Based Library For Userbots.
Home-page: https://github.com/GODBOYX/GODBOY
Author: GODBOYX
Author-email: rj05tilak@gmail.com
License: GNU AFFERO GENERAL PUBLIC LICENSE (v3)
Platform: UNKNOWN
Classifier: Programming Language :: Python :: 3
Classifier: License :: OSI Approved :: GNU General Public License v3 (GPLv3)
Classifier: Operating System :: OS Independent
Requires-Python: >=3.6
Requires-Dist: telethon
Requires-Dist: python-decouple (==3.3)
Requires-Dist: TgCrypto
Requires-Dist: python-dotenv (==0.15.0)
Requires-Dist: cloudscraper
